{
    "os": "Linux-5.19.0-45-generic-x86_64-with-glibc2.35",
    "python": "3.10.6",
    "heartbeatAt": "2023-06-20T03:19:54.790427",
    "startedAt": "2023-06-20T03:19:53.926888",
    "docker": null,
    "cuda": null,
    "args": [
        "run"
    ],
    "state": "running",
    "program": "/home/pslowiq/.local/bin/kedro",
    "host": "pslowiq-NH5x-7xRCx-RDx",
    "username": "pslowiq",
    "executable": "/usr/bin/python3",
    "cpu_count": 6,
    "cpu_count_logical": 12,
    "cpu_freq": {
        "current": 3173.097916666666,
        "min": 800.0,
        "max": 4500.0
    },
    "cpu_freq_per_core": [
        {
            "current": 3999.461,
            "min": 800.0,
            "max": 4500.0
        },
        {
            "current": 2600.0,
            "min": 800.0,
            "max": 4500.0
        },
        {
            "current": 4041.49,
            "min": 800.0,
            "max": 4500.0
        },
        {
            "current": 2934.186,
            "min": 800.0,
            "max": 4500.0
        },
        {
            "current": 3738.916,
            "min": 800.0,
            "max": 4500.0
        },
        {
            "current": 2600.0,
            "min": 800.0,
            "max": 4500.0
        },
        {
            "current": 4014.702,
            "min": 800.0,
            "max": 4500.0
        },
        {
            "current": 4017.047,
            "min": 800.0,
            "max": 4500.0
        },
        {
            "current": 2600.0,
            "min": 800.0,
            "max": 4500.0
        },
        {
            "current": 4092.233,
            "min": 800.0,
            "max": 4500.0
        },
        {
            "current": 4090.893,
            "min": 800.0,
            "max": 4500.0
        },
        {
            "current": 4000.06,
            "min": 800.0,
            "max": 4500.0
        }
    ],
    "disk": {
        "total": 191.94259643554688,
        "used": 173.97187042236328
    },
    "gpu": "NVIDIA GeForce RTX 2060",
    "gpu_count": 1,
    "gpu_devices": [
        {
            "name": "NVIDIA GeForce RTX 2060",
            "memory_total": 6442450944
        }
    ],
    "memory": {
        "total": 15.327247619628906
    }
}
